cheinsteinpy/__init__.py
cheinsteinpy/api.py
cheinsteinpy/requestPage.py
cheinsteinpy/parsers/__init__.py
cheinsteinpy/parsers/answerParser.py
cheinsteinpy/parsers/cookieParser.py
cheinsteinpy/parsers/pageParser.py
cheinsteinpy/parsers/questionParser.py
cheinsteinpy-0.1.5.dist-info/METADATA
cheinsteinpy-0.1.5.dist-info/WHEEL
cheinsteinpy-0.1.5.dist-info/top_level.txt
cheinsteinpy-0.1.5.dist-info/RECORD
