Metadata-Version: 2.1
Name: cheinsteinpy
Version: 0.1.5
Summary: A Python library to get information from Chegg.
Home-page: https://github.com/DouglasTaylorSupportGroup/cheinstein.py
Author: jckli & okinahiru
License: UNKNOWN
Platform: UNKNOWN
Requires-Dist: requests
Requires-Dist: beautifulsoup4
